fntools/__init__.py
fntools/fntools.py
fntools-1.1.2.dist-info/DESCRIPTION.rst
fntools-1.1.2.dist-info/METADATA
fntools-1.1.2.dist-info/RECORD
fntools-1.1.2.dist-info/WHEEL
fntools-1.1.2.dist-info/metadata.json
fntools-1.1.2.dist-info/pbr.json
fntools-1.1.2.dist-info/top_level.txt
