Metadata-Version: 2.0
Name: fntools
Version: 1.1.2
Summary: Functional programming tools for data processing
Home-page: https://github.com/TaurusOlson/fntools
Author: Taurus Olson
Author-email: taurusolson@gmail.com
License: MIT
Keywords: functional programming tools data processing
Platform: UNKNOWN
Classifier: Programming Language :: Python :: 2.7
Classifier: Topic :: Utilities
